frequenz/dispatch/__init__.py
frequenz/dispatch/_actor_dispatcher.py
frequenz/dispatch/_bg_service.py
frequenz/dispatch/_dispatch.py
frequenz/dispatch/_dispatcher.py
frequenz/dispatch/_event.py
frequenz/dispatch/_merge_strategies.py
frequenz/dispatch/conftest.py
frequenz/dispatch/py.typed
frequenz_dispatch-1.0.2.dist-info/licenses/LICENSE
frequenz_dispatch-1.0.2.dist-info/METADATA
frequenz_dispatch-1.0.2.dist-info/WHEEL
frequenz_dispatch-1.0.2.dist-info/top_level.txt
frequenz_dispatch-1.0.2.dist-info/RECORD
